cdox/__init__.py
cdox/__main__.py
cdox/cdox.py
cdox-1.0.3.dist-info/LICENSE
cdox-1.0.3.dist-info/METADATA
cdox-1.0.3.dist-info/WHEEL
cdox-1.0.3.dist-info/entry_points.txt
cdox-1.0.3.dist-info/top_level.txt
cdox-1.0.3.dist-info/RECORD
