Metadata-Version: 2.1
Name: cdox
Version: 1.0.3
Summary: automate documentation of c projects
Home-page: https://github.com/breakthatbass/cdox
Author: Taylor Gamache
Author-email: gamache.taylor@gmail.com
License: MIT
Platform: UNKNOWN
